farfetch/__init__.py
farfetch/address_schema.py
farfetch/bag.py
farfetch/base.py
farfetch/brand.py
farfetch/category.py
farfetch/checkout_order.py
farfetch/city.py
farfetch/continent.py
farfetch/country.py
farfetch/currency.py
farfetch/guest_user.py
farfetch/merchant.py
farfetch/merchant_location.py
farfetch/order.py
farfetch/payment.py
farfetch/product.py
farfetch/returns.py
farfetch/search.py
farfetch/state.py
farfetch/user.py
farfetch/wishlist.py
farfetch/test/__init__.py
farfetch_api-0.1.11.dist-info/top_level.txt
farfetch_api-0.1.11.dist-info/METADATA
farfetch_api-0.1.11.dist-info/DESCRIPTION.rst
farfetch_api-0.1.11.dist-info/metadata.json
farfetch_api-0.1.11.dist-info/WHEEL
farfetch_api-0.1.11.dist-info/RECORD
